light_recurrent_unit_pytorch/__init__.py
light_recurrent_unit_pytorch/light_recurrent_unit.py
light_recurrent_unit_pytorch-0.1.1.dist-info/METADATA
light_recurrent_unit_pytorch-0.1.1.dist-info/WHEEL
light_recurrent_unit_pytorch-0.1.1.dist-info/licenses/LICENSE
light_recurrent_unit_pytorch-0.1.1.dist-info/RECORD
