Metadata-Version: 2.3
Name: light-recurrent-unit-pytorch
Version: 0.1.1
Summary: Light Recurrent Unit
Project-URL: Homepage, https://pypi.org/project/light-recurrent-unit-pytorch/
Project-URL: Repository, https://github.com/lucidrains/light-recurrent-unit-pytorch
Author-email: Phil Wang <lucidrains@gmail.com>
License: MIT License
License-File: LICENSE
Keywords: artificial intelligence,deep learning,recurrent neural networks
Classifier: Development Status :: 4 - Beta
Classifier: Intended Audience :: Developers
Classifier: License :: OSI Approved :: MIT License
Classifier: Programming Language :: Python :: 3.9
Classifier: Topic :: Scientific/Engineering :: Artificial Intelligence
Requires-Python: >=3.9
Requires-Dist: torch>=2.0
Provides-Extra: examples
Provides-Extra: test
Requires-Dist: pytest; extra == 'test'
